artist_getter/__init__.py
artist_getter-0.4.4.dist-info/LICENSE
artist_getter-0.4.4.dist-info/METADATA
artist_getter-0.4.4.dist-info/WHEEL
artist_getter-0.4.4.dist-info/top_level.txt
artist_getter-0.4.4.dist-info/RECORD
