Metadata-Version: 2.1
Name: artist_getter
Version: 0.4.4
Summary: Getty ULAN and WikiData scraping utilities for artists
Home-page: https://github.com/fangyizhu/artist-getter
Author: Jay Mollica, Fangyi Zhu
Keywords: Getty Art ULAN WikiData Artist Artwork Museums
Classifier: Intended Audience :: Developers
Classifier: Intended Audience :: Information Technology
Classifier: Intended Audience :: Education
Classifier: Intended Audience :: Other Audience
Classifier: License :: Free for non-commercial use
Classifier: Programming Language :: Python :: 3.12
License-File: LICENSE
Requires-Dist: pycurl
Requires-Dist: python-Levenshtein
